zodburi/__init__.py
zodburi/datatypes.py
zodburi/resolvers.py
zodburi/tests/__init__.py
zodburi/tests/test___init__.py
zodburi/tests/test_datatypes.py
zodburi/tests/test_resolvers.py
zodburi-3.0.0.dist-info/LICENSE.txt
zodburi-3.0.0.dist-info/METADATA
zodburi-3.0.0.dist-info/WHEEL
zodburi-3.0.0.dist-info/entry_points.txt
zodburi-3.0.0.dist-info/top_level.txt
zodburi-3.0.0.dist-info/RECORD
