Metadata-Version: 2.2
Name: zodburi
Version: 3.0.0
Summary: Construct ZODB storage instances from URIs.
Author-email: Chris Rossi <pylons-discuss@googlegroups.com>
Project-URL: Homepage, https://docs.pylonsproject.org/projects/zodburi/en/latest/
Project-URL: Repository, https://github.com/Pylons/zodburi
Project-URL: Issues, https://github.com/Pylons/zodburi/issues
Project-URL: Changelog, https://github.com/Pylons/zodburi/blob/master/CHANGES.rst
Keywords: zodb,zodbconn
Classifier: Intended Audience :: Developers
Classifier: Programming Language :: Python
Classifier: Programming Language :: Python :: 3
Classifier: Programming Language :: Python :: 3.9
Classifier: Programming Language :: Python :: 3.10
Classifier: Programming Language :: Python :: 3.11
Classifier: Programming Language :: Python :: 3.12
Classifier: Programming Language :: Python :: 3.13
Classifier: Programming Language :: Python :: Implementation :: CPython
Classifier: Programming Language :: Python :: Implementation :: PyPy
Classifier: License :: Repoze Public License
Requires-Python: >=3.9
License-File: LICENSE.txt
Requires-Dist: ZODB
Requires-Dist: ZConfig
Requires-Dist: ZEO
Provides-Extra: testing
Requires-Dist: pytest; extra == "testing"
Requires-Dist: pytest-cov; extra == "testing"
Requires-Dist: check-manifest; extra == "testing"
Provides-Extra: docs
Requires-Dist: Sphinx; extra == "docs"
Requires-Dist: pylons-sphinx-themes; extra == "docs"
